taker/__init__.py
taker/activations.py
taker/data/imagenet_birds.json
taker/data/llama_most_common_tokens.json
taker/data/pytest-code-local/dataset_dict.json
taker/data/pytest-code-local/test/data-00000-of-00001.arrow
taker/data/pytest-code-local/test/dataset_info.json
taker/data/pytest-code-local/test/state.json
taker/data/pytest-code-local/train/data-00000-of-00001.arrow
taker/data/pytest-code-local/train/dataset_info.json
taker/data/pytest-code-local/train/state.json
taker/data/pytest-pile-local/dataset_dict.json
taker/data/pytest-pile-local/test/data-00000-of-00001.arrow
taker/data/pytest-pile-local/test/dataset_info.json
taker/data/pytest-pile-local/test/state.json
taker/data/pytest-pile-local/train/data-00000-of-00001.arrow
taker/data/pytest-pile-local/train/dataset_info.json
taker/data/pytest-pile-local/train/state.json
taker/data_classes.py
taker/detoxify.py
taker/eval.py
taker/hooks.py
taker/mia.py
taker/model.py
taker/model_maps.py
taker/model_repos.py
taker/nn.py
taker/parser.py
taker/prune.py
taker/scoring.py
taker/texts.py
taker/vit_processor.py
taker-1.2.3.dist-info/METADATA
taker-1.2.3.dist-info/WHEEL
taker-1.2.3.dist-info/RECORD
