Metadata-Version: 2.3
Name: taker
Version: 1.2.3
Summary: Tools for Transformer Activations Knowledge ExtRaction
Author: Nicky Pochinkov
Requires-Python: >=3.9,<4.0
Classifier: License :: OSI Approved :: MIT License
Classifier: Operating System :: OS Independent
Classifier: Programming Language :: Python :: 3
Classifier: Programming Language :: Python :: 3.9
Classifier: Programming Language :: Python :: 3.10
Classifier: Programming Language :: Python :: 3.11
Classifier: Programming Language :: Python :: 3.12
Classifier: Programming Language :: Python :: 3.13
Provides-Extra: cuda
Requires-Dist: accelerate (>=1.2.0)
Requires-Dist: antlr4-python3-runtime (==4.11.1)
Requires-Dist: datasets (>=2.9.0)
Requires-Dist: einops (>=0.6.0)
Requires-Dist: evaluate (>=0.4.0)
Requires-Dist: lm-eval (>=0.4.3)
Requires-Dist: numexpr (>=2.7.0)
Requires-Dist: numpy (>=1.23)
Requires-Dist: pandas (>=2.0.0)
Requires-Dist: scipy (>=1.11.1)
Requires-Dist: sentencepiece (>=0.1.99)
Requires-Dist: tokenizers (>=0.21.0)
Requires-Dist: torch (>=2.0.0)
Requires-Dist: transformers (>=4.45.2)
Requires-Dist: wandb (>=0.17.6)
Requires-Dist: welford-torch (>=0.2.4)
Requires-Dist: zstandard (>=0.19.0)
Project-URL: Repository, https://github.com/nickypro/taker
